varsync/__init__.py
varsync/cli.py
varsync/varsync.py
varsync-1.16.dist-info/METADATA
varsync-1.16.dist-info/WHEEL
varsync-1.16.dist-info/entry_points.txt
varsync-1.16.dist-info/top_level.txt
varsync-1.16.dist-info/RECORD
