Metadata-Version: 2.1
Name: varsync
Version: 1.16
Summary: A Python package for managing variables with a MySQL backend.
Home-page: https://github.com/Sriharan-S/varsync
Author: Sriharan
Author-email: sriharan2544@gmail.com
Classifier: Programming Language :: Python :: 3
Classifier: Operating System :: OS Independent
Requires-Python: >=3.6
Requires-Dist: mysql-connector-python
